kaszubski_translate_Szymtest/__init__.py
kaszubski_translate_Szymtest/a.py
kaszubski_tlumacz-1.0.3.dist-info/LICENSE
kaszubski_tlumacz-1.0.3.dist-info/METADATA
kaszubski_tlumacz-1.0.3.dist-info/WHEEL
kaszubski_tlumacz-1.0.3.dist-info/top_level.txt
kaszubski_tlumacz-1.0.3.dist-info/RECORD
