Metadata-Version: 2.1
Name: kaszubski-tlumacz
Version: 1.0.3
Summary: Pakiet tłumaczący z polkiego na kaszubski i odwrotnie
Author: Szymtest
Author-email: olstows30@gmail.com
Classifier: Programming Language :: Python :: 3
Classifier: License :: OSI Approved :: MIT License
Classifier: Operating System :: OS Independent
Requires-Python: >=3.6
License-File: LICENSE
